Metadata-Version: 2.4
Name: mcp-server-poc-rahmac
Version: 0.1.2
Summary: A simple MCP (Model Context Protocol) Server example
Author-email: Rah McRae <r.mcrae@fetchrewards.com>
License: MIT
Project-URL: Homepage, https://github.com/rahmac/mcp_poc
Project-URL: Repository, https://github.com/rahmac/mcp_poc
Project-URL: Issues, https://github.com/rahmac/mcp_poc/issues
Classifier: Development Status :: 3 - Alpha
Classifier: Intended Audience :: Developers
Classifier: License :: OSI Approved :: MIT License
Classifier: Programming Language :: Python :: 3
Classifier: Programming Language :: Python :: 3.8
Classifier: Programming Language :: Python :: 3.9
Classifier: Programming Language :: Python :: 3.10
Classifier: Programming Language :: Python :: 3.11
Classifier: Programming Language :: Python :: 3.12
Requires-Python: >=3.8
Requires-Dist: mcp>=1.0.0
Requires-Dist: pydantic>=2.0.0
Requires-Dist: anyio>=3.0.0
Provides-Extra: dev
Requires-Dist: pytest>=7.0.0; extra == "dev"
Requires-Dist: pytest-asyncio>=0.21.0; extra == "dev"
Requires-Dist: black>=23.0.0; extra == "dev"
Requires-Dist: isort>=5.0.0; extra == "dev"
Requires-Dist: mypy>=1.0.0; extra == "dev"
